{
  "words" : [ {
    "entry" : {
      "id" : 1,
      "form" : "no"
    },
    "translations" : [ {
      "title" : "漢字仮名混じり転写",
      "forms" : [ "我" ]
    }, {
      "title" : "体言",
      "forms" : [ "わたし", "私" ]
    } ],
    "tags" : [ ],
    "contents" : [ {
      "title" : "用法",
      "text" : "一般的な一人称代名詞である。"
    }, {
      "title" : "同根語",
      "text" : "nau.ar"
    } ],
    "variations" : [ ]
  }, {
    "entry" : {
      "id" : 2,
      "form" : "ma"
    },
    "translations" : [ {
      "title" : "漢字仮名混じり転写",
      "forms" : [ "汝" ]
    }, {
      "title" : "体言",
      "forms" : [ "あなた", "貴方" ]
    } ],
    "tags" : [ ],
    "contents" : [ {
      "title" : "用法",
      "text" : "代表的な二人称代名詞である。"
    }, {
      "title" : "同根語",
      "text" : "mua2.pk\náma.bt\namua.ar"
    } ],
    "variations" : [ ]
  }, {
    "entry" : {
      "id" : 3,
      "form" : "a"
    },
    "translations" : [ {
      "title" : "漢字仮名混じり転写",
      "forms" : [ "あ", "噫" ]
    }, {
      "title" : "叫詞",
      "forms" : [ "ああ", "えっと" ]
    } ],
    "tags" : [ ],
    "contents" : [ {
      "title" : "同根語",
      "text" : "a.pk\ná.bt\nhá.bt"
    } ],
    "variations" : [ ]
  }, {
    "entry" : {
      "id" : 4,
      "form" : "a"
    },
    "translations" : [ {
      "title" : "漢字仮名混じり転写",
      "forms" : [ "あ", "之" ]
    }, {
      "title" : "格助詞",
      "forms" : [ "～の" ]
    } ],
    "tags" : [ ],
    "contents" : [ {
      "title" : "同根語",
      "text" : "a.ar\na.pk\nanl.ln\n-án.bt"
    } ],
    "variations" : [ ]
  }, {
    "entry" : {
      "id" : 5,
      "form" : "(a)c-u"
    },
    "translations" : [ {
      "title" : "漢字仮名混じり転写",
      "forms" : [ "能す" ]
    }, {
      "title" : "補助用言",
      "forms" : [ "～できる", "～される" ]
    } ],
    "tags" : [ "為活用" ],
    "contents" : [ {
      "title" : "用法",
      "text" : "受身、自発、可能など無意識にできることを示す。"
    }, {
      "title" : "同根語",
      "text" : "acau.ar\nácahúḷ.bt"
    } ],
    "variations" : [ {
      "title" : "終止形",
      "form" : "acu"
    }, {
      "title" : "連体形",
      "form" : "acola"
    }, {
      "title" : "連用形",
      "form" : "aco"
    }, {
      "title" : "命令形",
      "form" : "aci"
    } ]
  }, {
    "entry" : {
      "id" : 6,
      "form" : "ata-lu"
    },
    "translations" : [ {
      "title" : "漢字仮名混じり転写",
      "forms" : [ "目る" ]
    }, {
      "title" : "用言",
      "forms" : [ "見る" ]
    } ],
    "tags" : [ ],
    "contents" : [ {
      "title" : "同根語",
      "text" : "aḍuhazoúḷ.bt"
    } ],
    "variations" : [ {
      "title" : "終止形",
      "form" : "atalu"
    }, {
      "title" : "連体形",
      "form" : "atala"
    }, {
      "title" : "連用形",
      "form" : "ata"
    }, {
      "title" : "命令形",
      "form" : "ataci"
    } ]
  }, {
    "entry" : {
      "id" : 7,
      "form" : "ai"
    },
    "translations" : [ {
      "title" : "漢字仮名混じり転写",
      "forms" : [ "冠" ]
    }, {
      "title" : "体言",
      "forms" : [ "冠", "かんむり" ]
    } ],
    "tags" : [ "牌語借用" ],
    "contents" : [ {
      "title" : "同根語",
      "text" : "ai2.pk"
    } ],
    "variations" : [ ]
  }, {
    "entry" : {
      "id" : 8,
      "form" : "eka-lu"
    },
    "translations" : [ {
      "title" : "漢字仮名混じり転写",
      "forms" : [ "光る" ]
    }, {
      "title" : "用言",
      "forms" : [ "光る" ]
    } ],
    "tags" : [ ],
    "contents" : [ {
      "title" : "同根語",
      "text" : "aik2.pk\nraikqt.ln\naika.ar\nkád.bt\nkádúḷ.bt\nek.bt"
    } ],
    "variations" : [ {
      "title" : "終止形",
      "form" : "ekalu"
    }, {
      "title" : "連体形",
      "form" : "ekala"
    }, {
      "title" : "連用形",
      "form" : "eka"
    }, {
      "title" : "命令形",
      "form" : "ekaci"
    } ]
  }, {
    "entry" : {
      "id" : 9,
      "form" : "asi"
    },
    "translations" : [ {
      "title" : "漢字仮名混じり転写",
      "forms" : [ "一" ]
    }, {
      "title" : "体言",
      "forms" : [ "一", "いち", "1" ]
    } ],
    "tags" : [ ],
    "contents" : [ ],
    "variations" : [ ]
  }, {
    "entry" : {
      "id" : 10,
      "form" : "ata"
    },
    "translations" : [ {
      "title" : "漢字仮名混じり転写",
      "forms" : [ "加た" ]
    }, {
      "title" : "格助詞",
      "forms" : [ "～と" ]
    } ],
    "tags" : [ ],
    "contents" : [ ],
    "variations" : [ ]
  }, {
    "entry" : {
      "id" : 11,
      "form" : "ata"
    },
    "translations" : [ {
      "title" : "漢字仮名混じり転写",
      "forms" : [ "目" ]
    }, {
      "title" : "体言",
      "forms" : [ "目" ]
    } ],
    "tags" : [ ],
    "contents" : [ {
      "title" : "同根語",
      "text" : "ta1.pk\nata.ar\nadha.bt\nqtaa.ln"
    } ],
    "variations" : [ ]
  }, {
    "entry" : {
      "id" : 12,
      "form" : "c-u"
    },
    "translations" : [ {
      "title" : "漢字仮名混じり転写",
      "forms" : [ "為" ]
    }, {
      "title" : "用言",
      "forms" : [ "する" ]
    } ],
    "tags" : [ "為活用" ],
    "contents" : [ {
      "title" : "同根語",
      "text" : "zau.pk\nchauchu.ar\nzúḷ.bt\nzau.ln"
    } ],
    "variations" : [ {
      "title" : "終止形",
      "form" : "cu"
    }, {
      "title" : "連体形",
      "form" : "cola"
    }, {
      "title" : "連用形",
      "form" : "co"
    }, {
      "title" : "命令形",
      "form" : "ci"
    } ]
  }, {
    "entry" : {
      "id" : 13,
      "form" : "ca"
    },
    "translations" : [ {
      "title" : "漢字仮名混じり転写",
      "forms" : [ "女" ]
    }, {
      "title" : "体言",
      "forms" : [ "女" ]
    } ],
    "tags" : [ ],
    "contents" : [ {
      "title" : "同根語",
      "text" : "sa1.pk\nusa.ar\n-sa.ar\nsá.bt\nsa.ln"
    } ],
    "variations" : [ ]
  }, {
    "entry" : {
      "id" : 14,
      "form" : "lij-u"
    },
    "translations" : [ {
      "title" : "漢字仮名混じり転写",
      "forms" : [ "須ゆ" ]
    }, {
      "title" : "用言",
      "forms" : [ "しなければならない" ]
    } ],
    "tags" : [ ],
    "contents" : [ {
      "title" : "同根語",
      "text" : "zalloúḷ.bt"
    } ],
    "variations" : [ {
      "title" : "終止形",
      "form" : "liju"
    }, {
      "title" : "連体形",
      "form" : "lija"
    }, {
      "title" : "連用形",
      "form" : "lie"
    }, {
      "title" : "命令形",
      "form" : "lii"
    } ]
  }, {
    "entry" : {
      "id" : 15,
      "form" : "cema-lu"
    },
    "translations" : [ {
      "title" : "漢字仮名混じり転写",
      "forms" : [ "言る" ]
    }, {
      "title" : "用言",
      "forms" : [ "言う", "話す" ]
    } ],
    "tags" : [ ],
    "contents" : [ {
      "title" : "同根語",
      "text" : "zepha.bt\ncepatepa.bt\nchepo.ar\nzep1.pk"
    } ],
    "variations" : [ {
      "title" : "終止形",
      "form" : "cemalu"
    }, {
      "title" : "連体形",
      "form" : "cemala"
    }, {
      "title" : "連用形",
      "form" : "cema"
    }, {
      "title" : "命令形",
      "form" : "cemaci"
    } ]
  }, {
    "entry" : {
      "id" : 16,
      "form" : "cemo"
    },
    "translations" : [ {
      "title" : "漢字仮名混じり転写",
      "forms" : [ "月" ]
    }, {
      "title" : "体言",
      "forms" : [ "月" ]
    } ],
    "tags" : [ ],
    "contents" : [ {
      "title" : "同根語",
      "text" : "xemo.ar\nxqmo.ln\nxem1.pk"
    } ],
    "variations" : [ ]
  }, {
    "entry" : {
      "id" : 17,
      "form" : "cik-u"
    },
    "translations" : [ {
      "title" : "漢字仮名混じり転写",
      "forms" : [ "席く", "座く" ]
    }, {
      "title" : "用言",
      "forms" : [ "座る" ]
    } ],
    "tags" : [ ],
    "contents" : [ {
      "title" : "同根語",
      "text" : "ciwi.ar\ncikau.ar\ncy2.pk\nṣíkahúḷ.bt"
    } ],
    "variations" : [ {
      "title" : "終止形",
      "form" : "ciku"
    }, {
      "title" : "連体形",
      "form" : "cika"
    }, {
      "title" : "連用形",
      "form" : "cike"
    }, {
      "title" : "命令形",
      "form" : "ciki"
    } ]
  }, {
    "entry" : {
      "id" : 18,
      "form" : "cisa"
    },
    "translations" : [ {
      "title" : "漢字仮名混じり転写",
      "forms" : [ "足" ]
    }, {
      "title" : "体言",
      "forms" : [ "足" ]
    } ],
    "tags" : [ ],
    "contents" : [ {
      "title" : "同根語",
      "text" : "xisa.ar\nxi1.pk"
    } ],
    "variations" : [ ]
  }, {
    "entry" : {
      "id" : 19,
      "form" : "cak-u"
    },
    "translations" : [ {
      "title" : "漢字仮名混じり転写",
      "forms" : [ "来く" ]
    }, {
      "title" : "用言",
      "forms" : [ "来る" ]
    } ],
    "tags" : [ ],
    "contents" : [ {
      "title" : "同根語",
      "text" : "sak2.pk\nsakika.ar\nsrakkq.ln\ncákíkúḷ.bt\ncákíkaúḷ.bt\nsáka.bt\nsakká.bt\nrakkúḷ.bt"
    } ],
    "variations" : [ {
      "title" : "終止形",
      "form" : "caku"
    }, {
      "title" : "連体形",
      "form" : "caka"
    }, {
      "title" : "連用形",
      "form" : "cake"
    }, {
      "title" : "命令形",
      "form" : "caki"
    } ]
  }, {
    "entry" : {
      "id" : 20,
      "form" : "co-lu"
    },
    "translations" : [ {
      "title" : "漢字仮名混じり転写",
      "forms" : [ "上る" ]
    }, {
      "title" : "用言",
      "forms" : [ "上げる", "上がる" ]
    } ],
    "tags" : [ ],
    "contents" : [ {
      "title" : "同根語",
      "text" : "sau2.pk\nsau.ar\nsrau.ln"
    } ],
    "variations" : [ {
      "title" : "終止形",
      "form" : "colu"
    }, {
      "title" : "連体形",
      "form" : "cola"
    }, {
      "title" : "連用形",
      "form" : "co"
    }, {
      "title" : "命令形",
      "form" : "coci"
    } ]
  }, {
    "entry" : {
      "id" : 21,
      "form" : "com-u"
    },
    "translations" : [ {
      "title" : "漢字仮名混じり転写",
      "forms" : [ "積む" ]
    }, {
      "title" : "用言",
      "forms" : [ "積む" ]
    } ],
    "tags" : [ ],
    "contents" : [ {
      "title" : "同根語",
      "text" : "xom1.pk\nshomu.ar\nsljoomq.ln\nṣomúl.bt\nṣoma.bt\nṣomaúḷ.bt"
    } ],
    "variations" : [ {
      "title" : "終止形",
      "form" : "comu"
    }, {
      "title" : "連体形",
      "form" : "coma"
    }, {
      "title" : "連用形",
      "form" : "come"
    }, {
      "title" : "命令形",
      "form" : "comi"
    } ]
  }, {
    "entry" : {
      "id" : 22,
      "form" : "mo-lu"
    },
    "translations" : [ {
      "title" : "漢字仮名混じり転写",
      "forms" : [ "満る" ]
    }, {
      "title" : "用言",
      "forms" : [ "満ちる" ]
    } ],
    "tags" : [ ],
    "contents" : [ {
      "title" : "同根語",
      "text" : "bhoúḷ.bt"
    } ],
    "variations" : [ {
      "title" : "終止形",
      "form" : "molu"
    }, {
      "title" : "連体形",
      "form" : "mola"
    }, {
      "title" : "連用形",
      "form" : "mo"
    }, {
      "title" : "命令形",
      "form" : "moci"
    } ]
  }, {
    "entry" : {
      "id" : 23,
      "form" : "cu"
    },
    "translations" : [ {
      "title" : "漢字仮名混じり転写",
      "forms" : [ "何", "孰" ]
    }, {
      "title" : "体言",
      "forms" : [ "どれ", "何", "なに" ]
    } ],
    "tags" : [ ],
    "contents" : [ {
      "title" : "同根語",
      "text" : "susi.ar"
    } ],
    "variations" : [ ]
  }, {
    "entry" : {
      "id" : 24,
      "form" : "cuka"
    },
    "translations" : [ {
      "title" : "漢字仮名混じり転写",
      "forms" : [ "人" ]
    }, {
      "title" : "体言",
      "forms" : [ "人" ]
    } ],
    "tags" : [ ],
    "contents" : [ {
      "title" : "同根語",
      "text" : "cuk2.pk\nasuka.ar"
    } ],
    "variations" : [ ]
  }, {
    "entry" : {
      "id" : 25,
      "form" : "cuna"
    },
    "translations" : [ {
      "title" : "漢字仮名混じり転写",
      "forms" : [ "五" ]
    }, {
      "title" : "体言",
      "forms" : [ "五", "5" ]
    } ],
    "tags" : [ ],
    "contents" : [ {
      "title" : "同根語",
      "text" : "slqna.ln\nsuna.ar"
    } ],
    "variations" : [ ]
  }, {
    "entry" : {
      "id" : 26,
      "form" : "(e)m-u"
    },
    "translations" : [ {
      "title" : "漢字仮名混じり転写",
      "forms" : [ "在む" ]
    }, {
      "title" : "補助用言",
      "forms" : [ "～している" ]
    } ],
    "tags" : [ ],
    "contents" : [ {
      "title" : "同根語",
      "text" : "hemúl.bt\nhem.bt\naima.ar\naimq.ln\naim2.pk"
    } ],
    "variations" : [ {
      "title" : "終止形",
      "form" : "emu"
    }, {
      "title" : "連体形",
      "form" : "ema"
    }, {
      "title" : "連用形",
      "form" : "eme"
    }, {
      "title" : "命令形",
      "form" : "emi"
    } ]
  }, {
    "entry" : {
      "id" : 27,
      "form" : "(e)ema-lu"
    },
    "translations" : [ {
      "title" : "漢字仮名混じり転写",
      "forms" : [ "在る" ]
    }, {
      "title" : "補助用言",
      "forms" : [ "〜している" ]
    } ],
    "tags" : [ ],
    "contents" : [ {
      "title" : "同根語",
      "text" : "hemúl.bt\nhem.bt\naima.ar\naimq.ln\naim2.pk"
    }, {
      "title" : "文化",
      "text" : "近代語。現代では稀。"
    } ],
    "variations" : [ {
      "title" : "終止形",
      "form" : "eemalu"
    }, {
      "title" : "連体形",
      "form" : "eemala"
    }, {
      "title" : "連用形",
      "form" : "eema"
    }, {
      "title" : "命令形",
      "form" : "eemaci"
    } ]
  }, {
    "entry" : {
      "id" : 28,
      "form" : "ema"
    },
    "translations" : [ {
      "title" : "漢字仮名混じり転写",
      "forms" : [ "在" ]
    }, {
      "title" : "体言",
      "forms" : [ "存在" ]
    } ],
    "tags" : [ ],
    "contents" : [ {
      "title" : "同根語",
      "text" : "hemúl.bt\nhem.bt\naima.ar\naimq.ln\naim2.pk"
    } ],
    "variations" : [ ]
  }, {
    "entry" : {
      "id" : 29,
      "form" : "(e)mu-lu"
    },
    "translations" : [ {
      "title" : "漢字仮名混じり転写",
      "forms" : [ "如る" ]
    }, {
      "title" : "補助用言",
      "forms" : [ "～のようだ" ]
    } ],
    "tags" : [ ],
    "contents" : [ {
      "title" : "同根語",
      "text" : "em.pk\naimu.ar\naaim.ln\nema.bt"
    } ],
    "variations" : [ {
      "title" : "終止形",
      "form" : "emulu"
    }, {
      "title" : "連体形",
      "form" : "emula"
    }, {
      "title" : "連用形",
      "form" : "emu"
    }, {
      "title" : "命令形",
      "form" : "emuci"
    } ]
  }, {
    "entry" : {
      "id" : 30,
      "form" : "i"
    },
    "translations" : [ {
      "title" : "漢字仮名混じり転写",
      "forms" : [ "等" ]
    }, {
      "title" : "助詞",
      "forms" : [ "～ら", "～など" ]
    } ],
    "tags" : [ ],
    "contents" : [ {
      "title" : "同根語",
      "text" : "i.ar"
    } ],
    "variations" : [ ]
  }, {
    "entry" : {
      "id" : 31,
      "form" : "(i)-lu"
    },
    "translations" : [ {
      "title" : "漢字仮名混じり転写",
      "forms" : [ "心る" ]
    }, {
      "title" : "補助用言",
      "forms" : [ "～したい", "～だろう", "～させる" ]
    } ],
    "tags" : [ ],
    "contents" : [ {
      "title" : "用法",
      "text" : "意思、推量、使役など意識を表す。"
    }, {
      "title" : "同根語",
      "text" : "hia1.pk\nhiya.ar\nriya.ln\nheyáúḷ.bt\nhíja.bt\nha.bt\nrijúḷ.bt"
    } ],
    "variations" : [ {
      "title" : "終止形",
      "form" : "ilu"
    }, {
      "title" : "連体形",
      "form" : "ila"
    }, {
      "title" : "連用形",
      "form" : "i"
    }, {
      "title" : "命令形",
      "form" : "ici"
    } ]
  }, {
    "entry" : {
      "id" : 32,
      "form" : "ija-lu"
    },
    "translations" : [ {
      "title" : "漢字仮名混じり転写",
      "forms" : [ "心る" ]
    }, {
      "title" : "用言",
      "forms" : [ "思う" ]
    } ],
    "tags" : [ ],
    "contents" : [ {
      "title" : "同根語",
      "text" : "hia1.pk\nhiya.ar\nriya.ln\nheyáúḷ.bt\nhíja.bt\nha.bt\nrijúḷ.bt\n"
    } ],
    "variations" : [ {
      "title" : "終止形",
      "form" : "ijalu"
    }, {
      "title" : "連体形",
      "form" : "ijala"
    }, {
      "title" : "連用形",
      "form" : "ija"
    }, {
      "title" : "命令形",
      "form" : "ijaci"
    } ]
  }, {
    "entry" : {
      "id" : 33,
      "form" : "meccuku"
    },
    "translations" : [ {
      "title" : "漢字仮名混じり転写",
      "forms" : [ "牌人" ]
    }, {
      "title" : "体言",
      "forms" : [ "パイグ人" ]
    } ],
    "tags" : [ "牌語借用" ],
    "contents" : [ ],
    "variations" : [ ]
  }, {
    "entry" : {
      "id" : 34,
      "form" : "iku"
    },
    "translations" : [ {
      "title" : "漢字仮名混じり転写",
      "forms" : [ "二" ]
    }, {
      "title" : "体言",
      "forms" : [ "二" ]
    } ],
    "tags" : [ ],
    "contents" : [ {
      "title" : "同根語",
      "text" : "ríka.bt\nik2.pk\niku.ar"
    } ],
    "variations" : [ ]
  }, {
    "entry" : {
      "id" : 35,
      "form" : "inuci"
    },
    "translations" : [ {
      "title" : "漢字仮名混じり転写",
      "forms" : [ "川" ]
    }, {
      "title" : "体言",
      "forms" : [ "川" ]
    } ],
    "tags" : [ ],
    "contents" : [ {
      "title" : "同根語",
      "text" : "nut2.pk\ninusi.ar"
    } ],
    "variations" : [ ]
  }, {
    "entry" : {
      "id" : 36,
      "form" : "jano"
    },
    "translations" : [ {
      "title" : "漢字仮名混じり転写",
      "forms" : [ "横" ]
    }, {
      "title" : "体言",
      "forms" : [ "横" ]
    } ],
    "tags" : [ ],
    "contents" : [ {
      "title" : "同根語",
      "text" : "yanio.ar"
    } ],
    "variations" : [ ]
  }, {
    "entry" : {
      "id" : 37,
      "form" : "ka"
    },
    "translations" : [ {
      "title" : "漢字仮名混じり転写",
      "forms" : [ "筆" ]
    }, {
      "title" : "体言",
      "forms" : [ "筆" ]
    } ],
    "tags" : [ "牌語借用" ],
    "contents" : [ {
      "title" : "同根語",
      "text" : "kua2.pk"
    } ],
    "variations" : [ ]
  }, {
    "entry" : {
      "id" : 38,
      "form" : "kani"
    },
    "translations" : [ {
      "title" : "漢字仮名混じり転写",
      "forms" : [ "火" ]
    }, {
      "title" : "体言",
      "forms" : [ "火" ]
    } ],
    "tags" : [ ],
    "contents" : [ {
      "title" : "同根語",
      "text" : "kan1.pk\ngháni.bt\nghánúḷ.bt"
    } ],
    "variations" : [ ]
  }, {
    "entry" : {
      "id" : 39,
      "form" : "nagamu"
    },
    "translations" : [ {
      "title" : "漢字仮名混じり転写",
      "forms" : [ "四" ]
    }, {
      "title" : "体言",
      "forms" : [ "四" ]
    } ],
    "tags" : [ ],
    "contents" : [ {
      "title" : "同根語",
      "text" : "ap1.pk\nnami.ar"
    } ],
    "variations" : [ ]
  }, {
    "entry" : {
      "id" : 40,
      "form" : "naga"
    },
    "translations" : [ {
      "title" : "漢字仮名混じり転写",
      "forms" : [ "四" ]
    }, {
      "title" : "体言",
      "forms" : [ "四" ]
    } ],
    "tags" : [ ],
    "contents" : [ {
      "title" : "同根語",
      "text" : "ap1.pk\nnami.ar"
    } ],
    "variations" : [ ]
  }, {
    "entry" : {
      "id" : 41,
      "form" : "nagan"
    },
    "translations" : [ {
      "title" : "漢字仮名混じり転写",
      "forms" : [ "四" ]
    }, {
      "title" : "体言",
      "forms" : [ "四" ]
    } ],
    "tags" : [ ],
    "contents" : [ {
      "title" : "同根語",
      "text" : "ap1.pk\nnami.ar"
    } ],
    "variations" : [ ]
  }, {
    "entry" : {
      "id" : 42,
      "form" : "keca"
    },
    "translations" : [ {
      "title" : "漢字仮名混じり転写",
      "forms" : [ "絵" ]
    }, {
      "title" : "体言",
      "forms" : [ "絵" ]
    } ],
    "tags" : [ ],
    "contents" : [ {
      "title" : "同根語",
      "text" : "qexua.ar"
    } ],
    "variations" : [ ]
  }, {
    "entry" : {
      "id" : 43,
      "form" : "kicu"
    },
    "translations" : [ {
      "title" : "漢字仮名混じり転写",
      "forms" : [ "頬" ]
    }, {
      "title" : "体言",
      "forms" : [ "頬" ]
    } ],
    "tags" : [ ],
    "contents" : [ {
      "title" : "同根語",
      "text" : "kisu.ar"
    } ],
    "variations" : [ ]
  }, {
    "entry" : {
      "id" : 44,
      "form" : "kija"
    },
    "translations" : [ {
      "title" : "漢字仮名混じり転写",
      "forms" : [ "日" ]
    }, {
      "title" : "体言",
      "forms" : [ "太陽", "日" ]
    } ],
    "tags" : [ ],
    "contents" : [ {
      "title" : "同根語",
      "text" : "ákíjam.bt\nkia1.pk"
    } ],
    "variations" : [ ]
  }, {
    "entry" : {
      "id" : 45,
      "form" : "mani"
    },
    "translations" : [ {
      "title" : "漢字仮名混じり転写",
      "forms" : [ "字" ]
    }, {
      "title" : "体言",
      "forms" : [ "字", "文字" ]
    } ],
    "tags" : [ ],
    "contents" : [ {
      "title" : "同根語",
      "text" : "báni.bt\nman1.pk"
    } ],
    "variations" : [ ]
  }, {
    "entry" : {
      "id" : 46,
      "form" : "manicoma"
    },
    "translations" : [ {
      "title" : "漢字仮名混じり転写",
      "forms" : [ "字積" ]
    }, {
      "title" : "体言",
      "forms" : [ "マニソマ" ]
    } ],
    "tags" : [ ],
    "contents" : [ {
      "title" : "文化",
      "text" : "ラネーメ圏発祥のカードゲーム、基本的には山札から何枚かカードを引いて、それらに書いてある燐字を組み合わせて字を作って遊ぶ。投げ棒を使って引くカードを制限したり、派生的なルールが多々ある。リパライン語圏では下にリパライン語で燐字の意味が書いてある場合がある。"
    } ],
    "variations" : [ ]
  }, {
    "entry" : {
      "id" : 47,
      "form" : "me"
    },
    "translations" : [ {
      "title" : "漢字仮名混じり転写",
      "forms" : [ "茲" ]
    }, {
      "title" : "体言",
      "forms" : [ "これ" ]
    } ],
    "tags" : [ ],
    "contents" : [ {
      "title" : "用法",
      "text" : "属格では用いず、代わりにkaが用いられる。"
    } ],
    "variations" : [ ]
  }, {
    "entry" : {
      "id" : 48,
      "form" : "medu"
    },
    "translations" : [ {
      "title" : "漢字仮名混じり転写",
      "forms" : [ "闇" ]
    }, {
      "title" : "体言",
      "forms" : [ "闇" ]
    } ],
    "tags" : [ ],
    "contents" : [ ],
    "variations" : [ ]
  }, {
    "entry" : {
      "id" : 49,
      "form" : "kan"
    },
    "translations" : [ {
      "title" : "漢字仮名混じり転写",
      "forms" : [ "処" ]
    }, {
      "title" : "格助詞",
      "forms" : [ "〜で", "〜に", "処格" ]
    } ],
    "tags" : [ "牌語借用", "牌語借用慣用音" ],
    "contents" : [ ],
    "variations" : [ ]
  }, {
    "entry" : {
      "id" : 50,
      "form" : "mema"
    },
    "translations" : [ {
      "title" : "漢字仮名混じり転写",
      "forms" : [ "地" ]
    }, {
      "title" : "体言",
      "forms" : [ "土地", "世界" ]
    } ],
    "tags" : [ ],
    "contents" : [ ],
    "variations" : [ ]
  }, {
    "entry" : {
      "id" : 51,
      "form" : "moku"
    },
    "translations" : [ {
      "title" : "漢字仮名混じり転写",
      "forms" : [ "輩" ]
    }, {
      "title" : "体言",
      "forms" : [ "兄弟" ]
    } ],
    "tags" : [ ],
    "contents" : [ ],
    "variations" : [ ]
  }, {
    "entry" : {
      "id" : 52,
      "form" : "moju"
    },
    "translations" : [ {
      "title" : "漢字仮名混じり転写",
      "forms" : [ "輩" ]
    }, {
      "title" : "体言",
      "forms" : [ "兄弟" ]
    } ],
    "tags" : [ ],
    "contents" : [ ],
    "variations" : [ ]
  }, {
    "entry" : {
      "id" : 53,
      "form" : "momo"
    },
    "translations" : [ {
      "title" : "漢字仮名混じり転写",
      "forms" : [ "手" ]
    }, {
      "title" : "体言",
      "forms" : [ "手" ]
    } ],
    "tags" : [ ],
    "contents" : [ {
      "title" : "同根語",
      "text" : "bhoma.bt"
    } ],
    "variations" : [ ]
  }, {
    "entry" : {
      "id" : 54,
      "form" : "muka"
    },
    "translations" : [ {
      "title" : "漢字仮名混じり転写",
      "forms" : [ "風" ]
    }, {
      "title" : "体言",
      "forms" : [ "風" ]
    } ],
    "tags" : [ ],
    "contents" : [ {
      "title" : "用法",
      "text" : "pua2.pk\nbhára.bt"
    } ],
    "variations" : [ ]
  }, {
    "entry" : {
      "id" : 55,
      "form" : "na"
    },
    "translations" : [ {
      "title" : "漢字仮名混じり転写",
      "forms" : [ "水" ]
    }, {
      "title" : "体言",
      "forms" : [ "水" ]
    } ],
    "tags" : [ ],
    "contents" : [ {
      "title" : "同根語",
      "text" : "nua2.pk\nnutta.bt"
    } ],
    "variations" : [ ]
  }, {
    "entry" : {
      "id" : 56,
      "form" : "cunasi"
    },
    "translations" : [ {
      "title" : "漢字仮名混じり転写",
      "forms" : [ "六" ]
    }, {
      "title" : "体言",
      "forms" : [ "六" ]
    } ],
    "tags" : [ ],
    "contents" : [ ],
    "variations" : [ ]
  }, {
    "entry" : {
      "id" : 57,
      "form" : "nisu"
    },
    "translations" : [ {
      "title" : "漢字仮名混じり転写",
      "forms" : [ "族" ]
    }, {
      "title" : "体言",
      "forms" : [ "民族", "部族" ]
    } ],
    "tags" : [ ],
    "contents" : [ {
      "title" : "同根語",
      "text" : "nímaṣ.bt\nnim2.pk"
    } ],
    "variations" : [ ]
  }, {
    "entry" : {
      "id" : 58,
      "form" : "nin"
    },
    "translations" : [ {
      "title" : "漢字仮名混じり転写",
      "forms" : [ "紙" ]
    }, {
      "title" : "体言",
      "forms" : [ "紙" ]
    } ],
    "tags" : [ ],
    "contents" : [ {
      "title" : "同根語",
      "text" : "nín.bt"
    } ],
    "variations" : [ ]
  }, {
    "entry" : {
      "id" : 59,
      "form" : "nomu"
    },
    "translations" : [ {
      "title" : "漢字仮名混じり転写",
      "forms" : [ "八" ]
    }, {
      "title" : "体言",
      "forms" : [ "八" ]
    } ],
    "tags" : [ "牌語借用" ],
    "contents" : [ {
      "title" : "文化",
      "text" : "タカン人は固有語だと思っているが、実際はパイグ語からの借用であり、固有語 *cunumu を置き換えた。"
    }, {
      "title" : "同根語",
      "text" : "nom2.pk"
    } ],
    "variations" : [ ]
  }, {
    "entry" : {
      "id" : 60,
      "form" : "non"
    },
    "translations" : [ {
      "title" : "漢字仮名混じり転写",
      "forms" : [ "八" ]
    }, {
      "title" : "体言",
      "forms" : [ "八" ]
    } ],
    "tags" : [ "牌語借用" ],
    "contents" : [ {
      "title" : "同根語",
      "text" : "nom2.pk"
    } ],
    "variations" : [ ]
  }, {
    "entry" : {
      "id" : 61,
      "form" : "nou"
    },
    "translations" : [ {
      "title" : "漢字仮名混じり転写",
      "forms" : [ "九" ]
    }, {
      "title" : "体言",
      "forms" : [ "九" ]
    } ],
    "tags" : [ ],
    "contents" : [ {
      "title" : "同根語",
      "text" : "naku.ar"
    } ],
    "variations" : [ ]
  }, {
    "entry" : {
      "id" : 62,
      "form" : "kamu"
    },
    "translations" : [ {
      "title" : "漢字仮名混じり転写",
      "forms" : [ "四" ]
    }, {
      "title" : "体言",
      "forms" : [ "四" ]
    } ],
    "tags" : [ ],
    "contents" : [ {
      "title" : "同根語",
      "text" : "cuna + nagamu の縮約である、死語cunagamuからの逆成。"
    } ],
    "variations" : [ ]
  }, {
    "entry" : {
      "id" : 63,
      "form" : "tadu"
    },
    "translations" : [ {
      "title" : "漢字仮名混じり転写",
      "forms" : [ "集" ]
    }, {
      "title" : "体言",
      "forms" : [ "集まり", "集団", "団体" ]
    } ],
    "tags" : [ ],
    "contents" : [ {
      "title" : "同根語",
      "text" : "dhárad.bt\ndat2.pk"
    } ],
    "variations" : [ ]
  }, {
    "entry" : {
      "id" : 64,
      "form" : "takameku"
    },
    "translations" : [ {
      "title" : "漢字仮名混じり転写",
      "forms" : [ "皇光" ]
    }, {
      "title" : "体言",
      "forms" : [ "皇光", "WP" ]
    } ],
    "tags" : [ ],
    "contents" : [ ],
    "variations" : [ ]
  }, {
    "entry" : {
      "id" : 65,
      "form" : "takan"
    },
    "translations" : [ {
      "title" : "漢字仮名混じり転写",
      "forms" : [ "皇" ]
    }, {
      "title" : "体言",
      "forms" : [ "皇神" ]
    }, {
      "title" : "修飾性体言",
      "forms" : [ "タカン民族の" ]
    } ],
    "tags" : [ ],
    "contents" : [ ],
    "variations" : [ ]
  }, {
    "entry" : {
      "id" : 66,
      "form" : "takamu"
    },
    "translations" : [ {
      "title" : "漢字仮名混じり転写",
      "forms" : [ "皇" ]
    }, {
      "title" : "体言",
      "forms" : [ "皇神" ]
    } ],
    "tags" : [ ],
    "contents" : [ ],
    "variations" : [ ]
  }, {
    "entry" : {
      "id" : 67,
      "form" : "ton"
    },
    "translations" : [ {
      "title" : "漢字仮名混じり転写",
      "forms" : [ "樽" ]
    }, {
      "title" : "体言",
      "forms" : [ "容器" ]
    } ],
    "tags" : [ ],
    "contents" : [ {
      "title" : "同根語",
      "text" : "tobwu.ar"
    } ],
    "variations" : [ ]
  }, {
    "entry" : {
      "id" : 68,
      "form" : "tunu"
    },
    "translations" : [ {
      "title" : "漢字仮名混じり転写",
      "forms" : [ "神" ]
    }, {
      "title" : "体言",
      "forms" : [ "神" ]
    } ],
    "tags" : [ ],
    "contents" : [ ],
    "variations" : [ ]
  }, {
    "entry" : {
      "id" : 69,
      "form" : "tuna"
    },
    "translations" : [ {
      "title" : "漢字仮名混じり転写",
      "forms" : [ "神" ]
    }, {
      "title" : "体言",
      "forms" : [ "神" ]
    } ],
    "tags" : [ ],
    "contents" : [ ],
    "variations" : [ ]
  }, {
    "entry" : {
      "id" : 70,
      "form" : "umu"
    },
    "translations" : [ {
      "title" : "漢字仮名混じり転写",
      "forms" : [ "三" ]
    }, {
      "title" : "体言",
      "forms" : [ "三" ]
    } ],
    "tags" : [ ],
    "contents" : [ ],
    "variations" : [ ]
  }, {
    "entry" : {
      "id" : 71,
      "form" : "cuneku"
    },
    "translations" : [ {
      "title" : "漢字仮名混じり転写",
      "forms" : [ "七" ]
    }, {
      "title" : "体言",
      "forms" : [ "七" ]
    } ],
    "tags" : [ ],
    "contents" : [ ],
    "variations" : [ ]
  }, {
    "entry" : {
      "id" : 72,
      "form" : "cac-u"
    },
    "translations" : [ {
      "title" : "漢字仮名混じり転写",
      "forms" : [ "恒す" ]
    }, {
      "title" : "用言",
      "forms" : [ "永遠である" ]
    } ],
    "tags" : [ ],
    "contents" : [ {
      "title" : "同根語",
      "text" : "caxou.ar"
    } ],
    "variations" : [ {
      "title" : "終止形",
      "form" : "cacu"
    }, {
      "title" : "連体形",
      "form" : "caca"
    }, {
      "title" : "連用形",
      "form" : "cace"
    }, {
      "title" : "命令形",
      "form" : "caci"
    } ]
  }, {
    "entry" : {
      "id" : 73,
      "form" : "(e)t-u"
    },
    "translations" : [ {
      "title" : "漢字仮名混じり転写",
      "forms" : [ "下つ" ]
    }, {
      "title" : "補助用言",
      "forms" : [ "〜なさる" ]
    } ],
    "tags" : [ ],
    "contents" : [ {
      "title" : "同根語",
      "text" : "rúṣ.bt"
    } ],
    "variations" : [ {
      "title" : "終止形",
      "form" : "etu"
    }, {
      "title" : "連体形",
      "form" : "eta"
    }, {
      "title" : "連用形",
      "form" : "ete"
    }, {
      "title" : "命令形",
      "form" : "eti"
    } ]
  }, {
    "entry" : {
      "id" : 74,
      "form" : "kan-u"
    },
    "translations" : [ {
      "title" : "漢字仮名混じり転写",
      "forms" : [ "火ぬ" ]
    }, {
      "title" : "用言",
      "forms" : [ "燃える" ]
    } ],
    "tags" : [ ],
    "contents" : [ {
      "title" : "同根語",
      "text" : "kan1.pk"
    } ],
    "variations" : [ {
      "title" : "終止形",
      "form" : "kanu"
    }, {
      "title" : "連体形",
      "form" : "kana"
    }, {
      "title" : "連用形",
      "form" : "kane"
    }, {
      "title" : "命令形",
      "form" : "kani"
    } ]
  }, {
    "entry" : {
      "id" : 75,
      "form" : "aim-u"
    },
    "translations" : [ {
      "title" : "漢字仮名混じり転写",
      "forms" : [ "在む" ]
    }, {
      "title" : "用言",
      "forms" : [ "在る" ]
    } ],
    "tags" : [ ],
    "contents" : [ {
      "title" : "同根語",
      "text" : "hemúl.bt\nhem.bt\naima.ar\naimq.ln\naim2.pk"
    } ],
    "variations" : [ {
      "title" : "終止形",
      "form" : "aimu"
    }, {
      "title" : "連体形",
      "form" : "aima"
    }, {
      "title" : "連用形",
      "form" : "aime"
    }, {
      "title" : "命令形",
      "form" : "aimi"
    } ]
  }, {
    "entry" : {
      "id" : 76,
      "form" : "mom-u"
    },
    "translations" : [ {
      "title" : "漢字仮名混じり転写",
      "forms" : [ "手む" ]
    }, {
      "title" : "用言",
      "forms" : [ "取る" ]
    } ],
    "tags" : [ ],
    "contents" : [ {
      "title" : "同根語",
      "text" : "hop1.pk"
    } ],
    "variations" : [ {
      "title" : "終止形",
      "form" : "momu"
    }, {
      "title" : "連体形",
      "form" : "moma"
    }, {
      "title" : "連用形",
      "form" : "mome"
    }, {
      "title" : "命令形",
      "form" : "momi"
    } ]
  }, {
    "entry" : {
      "id" : 77,
      "form" : "wac-u"
    },
    "translations" : [ {
      "title" : "漢字仮名混じり転写",
      "forms" : [ "無す" ]
    }, {
      "title" : "用言",
      "forms" : [ "無い" ]
    } ],
    "tags" : [ ],
    "contents" : [ ],
    "variations" : [ {
      "title" : "終止形",
      "form" : "wacu"
    }, {
      "title" : "連体形",
      "form" : "waca"
    }, {
      "title" : "連用形",
      "form" : "wace"
    }, {
      "title" : "命令形",
      "form" : "waci"
    } ]
  }, {
    "entry" : {
      "id" : 78,
      "form" : "cosa-lu"
    },
    "translations" : [ {
      "title" : "漢字仮名混じり転写",
      "forms" : [ "穏る" ]
    }, {
      "title" : "用言",
      "forms" : [ "穏やかである" ]
    } ],
    "tags" : [ ],
    "contents" : [ {
      "title" : "同根語",
      "text" : "shousa.ar"
    } ],
    "variations" : [ {
      "title" : "終止形",
      "form" : "cosalu"
    }, {
      "title" : "連体形",
      "form" : "cosala"
    }, {
      "title" : "連用形",
      "form" : "cosa"
    }, {
      "title" : "命令形",
      "form" : "cosaci"
    } ]
  }, {
    "entry" : {
      "id" : 79,
      "form" : "mor-lu"
    },
    "translations" : [ {
      "title" : "漢字仮名混じり転写",
      "forms" : [ "行る" ]
    }, {
      "title" : "用言",
      "forms" : [ "行く" ]
    } ],
    "tags" : [ ],
    "contents" : [ {
      "title" : "同根語",
      "text" : "bhoúḷ.bt"
    } ],
    "variations" : [ {
      "title" : "終止形",
      "form" : "morlu"
    }, {
      "title" : "連体形",
      "form" : "morla"
    }, {
      "title" : "連用形",
      "form" : "mor"
    }, {
      "title" : "命令形",
      "form" : "morci"
    } ]
  }, {
    "entry" : {
      "id" : 80,
      "form" : "aci-lu"
    },
    "translations" : [ {
      "title" : "漢字仮名混じり転写",
      "forms" : [ "辿る" ]
    }, {
      "title" : "用言",
      "forms" : [ "たどる", "なぞる" ]
    } ],
    "tags" : [ ],
    "contents" : [ {
      "title" : "同根語",
      "text" : "acii.ar\naccúḷ.bt\nacii.ln"
    } ],
    "variations" : [ {
      "title" : "終止形",
      "form" : "acilu"
    }, {
      "title" : "連体形",
      "form" : "acila"
    }, {
      "title" : "連用形",
      "form" : "aci"
    }, {
      "title" : "命令形",
      "form" : "acici"
    } ]
  }, {
    "entry" : {
      "id" : 81,
      "form" : "cema"
    },
    "translations" : [ {
      "title" : "漢字仮名混じり転写",
      "forms" : [ "言" ]
    }, {
      "title" : "体言",
      "forms" : [ "言語" ]
    } ],
    "tags" : [ ],
    "contents" : [ {
      "title" : "同根語",
      "text" : "zepha.bt\ncepatepa.bt\nchepo.ar\nzep1.pk"
    } ],
    "variations" : [ ]
  }, {
    "entry" : {
      "id" : 82,
      "form" : "co"
    },
    "translations" : [ {
      "title" : "漢字仮名混じり転写",
      "forms" : [ "上" ]
    }, {
      "title" : "体言",
      "forms" : [ "上" ]
    } ],
    "tags" : [ ],
    "contents" : [ {
      "title" : "同根語",
      "text" : "sau2.pk\nsau.ar\nsrau.ln"
    } ],
    "variations" : [ ]
  }, {
    "entry" : {
      "id" : 83,
      "form" : "aika"
    },
    "translations" : [ {
      "title" : "漢字仮名混じり転写",
      "forms" : [ "光" ]
    }, {
      "title" : "体言",
      "forms" : [ "光" ]
    } ],
    "tags" : [ ],
    "contents" : [ {
      "title" : "同根語",
      "text" : "aik2.pk\nraikqt.ln\naika.ar\nkád.bt\nkádúḷ.bt\nek.bt"
    } ],
    "variations" : [ ]
  }, {
    "entry" : {
      "id" : 84,
      "form" : "ija"
    },
    "translations" : [ {
      "title" : "漢字仮名混じり転写",
      "forms" : [ "心" ]
    }, {
      "title" : "体言",
      "forms" : [ "心" ]
    } ],
    "tags" : [ ],
    "contents" : [ {
      "title" : "同根語",
      "text" : "hia1.pk\nhiya.ar\nriya.ln\nheyáúḷ.bt\nhíja.bt\nha.bt\nrijúḷ.bt\n"
    } ],
    "variations" : [ ]
  }, {
    "entry" : {
      "id" : 85,
      "form" : "koli-lu"
    },
    "translations" : [ {
      "title" : "漢字仮名混じり転写",
      "forms" : [ "疲る" ]
    }, {
      "title" : "用言",
      "forms" : [ "疲れる" ]
    } ],
    "tags" : [ ],
    "contents" : [ {
      "title" : "同根語",
      "text" : "koli.bt"
    } ],
    "variations" : [ {
      "title" : "終止形",
      "form" : "kolilu"
    }, {
      "title" : "連体形",
      "form" : "kolila"
    }, {
      "title" : "連用形",
      "form" : "koli"
    }, {
      "title" : "命令形",
      "form" : "kolici"
    } ]
  }, {
    "entry" : {
      "id" : 86,
      "form" : "ka-lu"
    },
    "translations" : [ {
      "title" : "漢字仮名混じり転写",
      "forms" : [ "筆る" ]
    }, {
      "title" : "用言",
      "forms" : [ "書く" ]
    } ],
    "tags" : [ "牌語借用" ],
    "contents" : [ {
      "title" : "同根語",
      "text" : "kua2.pk"
    } ],
    "variations" : [ {
      "title" : "終止形",
      "form" : "kalu"
    }, {
      "title" : "連体形",
      "form" : "kala"
    }, {
      "title" : "連用形",
      "form" : "ka"
    }, {
      "title" : "命令形",
      "form" : "kaci"
    } ]
  }, {
    "entry" : {
      "id" : 87,
      "form" : "na-lu"
    },
    "translations" : [ {
      "title" : "漢字仮名混じり転写",
      "forms" : [ "水る" ]
    }, {
      "title" : "用言",
      "forms" : [ "流れる" ]
    } ],
    "tags" : [ ],
    "contents" : [ {
      "title" : "同根語",
      "text" : "nua2.pk\nnutta.bt"
    } ],
    "variations" : [ {
      "title" : "終止形",
      "form" : "nalu"
    }, {
      "title" : "連体形",
      "form" : "nala"
    }, {
      "title" : "連用形",
      "form" : "na"
    }, {
      "title" : "命令形",
      "form" : "naci"
    } ]
  }, {
    "entry" : {
      "id" : 88,
      "form" : "eka"
    },
    "translations" : [ {
      "title" : "漢字仮名混じり転写",
      "forms" : [ "光" ]
    }, {
      "title" : "体言",
      "forms" : [ "光" ]
    } ],
    "tags" : [ ],
    "contents" : [ {
      "title" : "同根語",
      "text" : "aik2.pk\nraikqt.ln\naika.ar\nkád.bt\nkádúḷ.bt\nek.bt"
    } ],
    "variations" : [ ]
  }, {
    "entry" : {
      "id" : 89,
      "form" : "ki"
    },
    "translations" : [ {
      "title" : "漢字仮名混じり転写",
      "forms" : [ "那", "彼" ]
    }, {
      "title" : "体言",
      "forms" : [ "あれ", "かれ", "彼", "あの人", "彼女" ]
    } ],
    "tags" : [ ],
    "contents" : [ ],
    "variations" : [ ]
  }, {
    "entry" : {
      "id" : 90,
      "form" : "ti"
    },
    "translations" : [ {
      "title" : "漢字仮名混じり転写",
      "forms" : [ "其" ]
    }, {
      "title" : "体言",
      "forms" : [ "それ" ]
    } ],
    "tags" : [ ],
    "contents" : [ {
      "title" : "同根語",
      "text" : "dí.bt"
    } ],
    "variations" : [ ]
  }, {
    "entry" : {
      "id" : 91,
      "form" : "uo"
    },
    "translations" : [ {
      "title" : "漢字仮名混じり転写",
      "forms" : [ "墨" ]
    }, {
      "title" : "体言",
      "forms" : [ "墨" ]
    } ],
    "tags" : [ "牌語借用", "牌語借用慣用音" ],
    "contents" : [ {
      "title" : "同根語",
      "text" : "huo2.pk"
    } ],
    "variations" : [ ]
  }, {
    "entry" : {
      "id" : 92,
      "form" : "concitu"
    },
    "translations" : [ {
      "title" : "漢字仮名混じり転写",
      "forms" : [ "周故" ]
    }, {
      "title" : "体言",
      "forms" : [ "革命" ]
    } ],
    "tags" : [ "牌語借用", "牌語借用慣用音" ],
    "contents" : [ ],
    "variations" : [ ]
  }, {
    "entry" : {
      "id" : 93,
      "form" : "ki"
    },
    "translations" : [ {
      "title" : "漢字仮名混じり転写",
      "forms" : [ "於" ]
    }, {
      "title" : "格助詞",
      "forms" : [ "〜を", "対格" ]
    } ],
    "tags" : [ ],
    "contents" : [ ],
    "variations" : [ ]
  }, {
    "entry" : {
      "id" : 94,
      "form" : "oca"
    },
    "translations" : [ {
      "title" : "漢字仮名混じり転写",
      "forms" : [ "来さ", "耒 " ]
    }, {
      "title" : "格助詞",
      "forms" : [ "〜から" ]
    } ],
    "tags" : [ ],
    "contents" : [ ],
    "variations" : [ ]
  }, {
    "entry" : {
      "id" : 95,
      "form" : "ju"
    },
    "translations" : [ {
      "title" : "漢字仮名混じり転写",
      "forms" : [ "亦" ]
    }, {
      "title" : "格助詞",
      "forms" : [ "列挙", "〜もまた" ]
    } ],
    "tags" : [ ],
    "contents" : [ ],
    "variations" : [ ]
  }, {
    "entry" : {
      "id" : 96,
      "form" : "men"
    },
    "translations" : [ {
      "title" : "漢字仮名混じり転写",
      "forms" : [ "通" ]
    }, {
      "title" : "格助詞",
      "forms" : [ "〜を経由して" ]
    } ],
    "tags" : [ ],
    "contents" : [ {
      "title" : "用法",
      "text" : "現代では稀。"
    } ],
    "variations" : [ ]
  }, {
    "entry" : {
      "id" : 97,
      "form" : "wa"
    },
    "translations" : [ {
      "title" : "漢字仮名混じり転写",
      "forms" : [ "而" ]
    }, {
      "title" : "接続助詞",
      "forms" : [ "〜して" ]
    } ],
    "tags" : [ ],
    "contents" : [ ],
    "variations" : [ ]
  }, {
    "entry" : {
      "id" : 98,
      "form" : "ken"
    },
    "translations" : [ {
      "title" : "漢字仮名混じり転写",
      "forms" : [ "即" ]
    }, {
      "title" : "接続助詞",
      "forms" : [ "〜したら" ]
    } ],
    "tags" : [ "牌語借用" ],
    "contents" : [ ],
    "variations" : [ ]
  }, {
    "entry" : {
      "id" : 99,
      "form" : "ja"
    },
    "translations" : [ {
      "title" : "漢字仮名混じり転写",
      "forms" : [ "や" ]
    }, {
      "title" : "副助詞",
      "forms" : [ "主題の副助詞", "〜は" ]
    } ],
    "tags" : [ ],
    "contents" : [ ],
    "variations" : [ ]
  }, {
    "entry" : {
      "id" : 100,
      "form" : "o"
    },
    "translations" : [ {
      "title" : "漢字仮名混じり転写",
      "forms" : [ "亦" ]
    }, {
      "title" : "副助詞",
      "forms" : [ "〜も" ]
    } ],
    "tags" : [ ],
    "contents" : [ ],
    "variations" : [ ]
  }, {
    "entry" : {
      "id" : 101,
      "form" : "tetu"
    },
    "translations" : [ {
      "title" : "漢字仮名混じり転写",
      "forms" : [ "唯" ]
    }, {
      "title" : "副助詞",
      "forms" : [ "〜だけ" ]
    } ],
    "tags" : [ ],
    "contents" : [ ],
    "variations" : [ ]
  }, {
    "entry" : {
      "id" : 102,
      "form" : "(a)ta"
    },
    "translations" : [ {
      "title" : "漢字仮名混じり転写",
      "forms" : [ "終" ]
    }, {
      "title" : "助詞",
      "forms" : [ "〜した" ]
    } ],
    "tags" : [ ],
    "contents" : [ {
      "title" : "用法",
      "text" : "すでに完了したことを示す。"
    } ],
    "variations" : [ ]
  }, {
    "entry" : {
      "id" : 103,
      "form" : "ut-u"
    },
    "translations" : [ {
      "title" : "漢字仮名混じり転写",
      "forms" : [ "下つ" ]
    }, {
      "title" : "用言",
      "forms" : [ "下がる", "下げる" ]
    } ],
    "tags" : [ ],
    "contents" : [ {
      "title" : "同根語",
      "text" : "rúṣ.bt"
    } ],
    "variations" : [ {
      "title" : "終止形",
      "form" : "utu"
    }, {
      "title" : "連体形",
      "form" : "uta"
    }, {
      "title" : "連用形",
      "form" : "ute"
    }, {
      "title" : "命令形",
      "form" : "uti"
    } ]
  }, {
    "entry" : {
      "id" : 104,
      "form" : "(e)co-lu"
    },
    "translations" : [ {
      "title" : "漢字仮名混じり転写",
      "forms" : [ "上る" ]
    }, {
      "title" : "補助用言",
      "forms" : [ "～させていただく" ]
    } ],
    "tags" : [ ],
    "contents" : [ {
      "title" : "同根語",
      "text" : "sau2.pk\nsau.ar\nsrau.ln"
    } ],
    "variations" : [ {
      "title" : "終止形",
      "form" : "ecolu"
    }, {
      "title" : "連体形",
      "form" : "ecola"
    }, {
      "title" : "連用形",
      "form" : "eco"
    }, {
      "title" : "命令形",
      "form" : "ecoci"
    } ]
  }, {
    "entry" : {
      "id" : 105,
      "form" : "(e)jan-u"
    },
    "translations" : [ {
      "title" : "漢字仮名混じり転写",
      "forms" : [ "生ぬ" ]
    }, {
      "title" : "補助用言",
      "forms" : [ "開始瞬間の助動詞" ]
    } ],
    "tags" : [ ],
    "contents" : [ ],
    "variations" : [ {
      "title" : "終止形",
      "form" : "ejanu"
    }, {
      "title" : "連体形",
      "form" : "ejana"
    }, {
      "title" : "連用形",
      "form" : "ejane"
    }, {
      "title" : "命令形",
      "form" : "ejani"
    } ]
  }, {
    "entry" : {
      "id" : 106,
      "form" : "(e)nit-u"
    },
    "translations" : [ {
      "title" : "漢字仮名混じり転写",
      "forms" : [ "入つ" ]
    }, {
      "title" : "補助用言",
      "forms" : [ "終了瞬間の助動詞" ]
    } ],
    "tags" : [ ],
    "contents" : [ ],
    "variations" : [ {
      "title" : "終止形",
      "form" : "enitu"
    }, {
      "title" : "連体形",
      "form" : "enita"
    }, {
      "title" : "連用形",
      "form" : "enite"
    }, {
      "title" : "命令形",
      "form" : "eniti"
    } ]
  }, {
    "entry" : {
      "id" : 107,
      "form" : "(e)mok-u"
    },
    "translations" : [ {
      "title" : "漢字仮名混じり転写",
      "forms" : [ "行く" ]
    }, {
      "title" : "補助用言",
      "forms" : [ "移動隔離の助動詞" ]
    } ],
    "tags" : [ ],
    "contents" : [ ],
    "variations" : [ {
      "title" : "終止形",
      "form" : "emoku"
    }, {
      "title" : "連体形",
      "form" : "emoka"
    }, {
      "title" : "連用形",
      "form" : "emoke"
    }, {
      "title" : "命令形",
      "form" : "emoki"
    } ]
  }, {
    "entry" : {
      "id" : 108,
      "form" : "(e)cak-u"
    },
    "translations" : [ {
      "title" : "漢字仮名混じり転写",
      "forms" : [ "来く" ]
    }, {
      "title" : "補助用言",
      "forms" : [ "移動接近の助動詞" ]
    } ],
    "tags" : [ ],
    "contents" : [ ],
    "variations" : [ {
      "title" : "終止形",
      "form" : "ecaku"
    }, {
      "title" : "連体形",
      "form" : "ecaka"
    }, {
      "title" : "連用形",
      "form" : "ecake"
    }, {
      "title" : "命令形",
      "form" : "ecaki"
    } ]
  }, {
    "entry" : {
      "id" : 109,
      "form" : "munconciccicuku"
    },
    "translations" : [ {
      "title" : "漢字仮名混じり転写",
      "forms" : [ "無周故し人" ]
    }, {
      "title" : "体言",
      "forms" : [ "反革命主義者" ]
    } ],
    "tags" : [ ],
    "contents" : [ ],
    "variations" : [ ]
  }, {
    "entry" : {
      "id" : 110,
      "form" : "unun-u"
    },
    "translations" : [ {
      "title" : "漢字仮名混じり転写",
      "forms" : [ "うぬぬ" ]
    }, {
      "title" : "用言",
      "forms" : [ "〜である" ]
    } ],
    "tags" : [ ],
    "contents" : [ ],
    "variations" : [ {
      "title" : "終止形",
      "form" : "ununu"
    }, {
      "title" : "連体形",
      "form" : "ununa"
    }, {
      "title" : "連用形",
      "form" : "unune"
    }, {
      "title" : "命令形",
      "form" : "ununi"
    } ]
  }, {
    "entry" : {
      "id" : 111,
      "form" : "mu"
    },
    "translations" : [ {
      "title" : "漢字仮名混じり転写",
      "forms" : [ "乎" ]
    }, {
      "title" : "助詞",
      "forms" : [ "疑問助詞", "〜か？" ]
    } ],
    "tags" : [ ],
    "contents" : [ ],
    "variations" : [ ]
  }, {
    "entry" : {
      "id" : 112,
      "form" : "cen"
    },
    "translations" : [ {
      "title" : "漢字仮名混じり転写",
      "forms" : [ "言" ]
    }, {
      "title" : "体言",
      "forms" : [ "〜語" ]
    } ],
    "tags" : [ "牌語借用" ],
    "contents" : [ ],
    "variations" : [ ]
  }, {
    "entry" : {
      "id" : 113,
      "form" : "kijacuka"
    },
    "translations" : [ {
      "title" : "漢字仮名混じり転写",
      "forms" : [ "日来之" ]
    }, {
      "title" : "人名",
      "forms" : [ "キヤスカ" ]
    } ],
    "tags" : [ ],
    "contents" : [ ],
    "variations" : [ ]
  }, {
    "entry" : {
      "id" : 114,
      "form" : "mon"
    },
    "translations" : [ {
      "title" : "漢字仮名混じり転写",
      "forms" : [ "米" ]
    }, {
      "title" : "体言",
      "forms" : [ "米" ]
    } ],
    "tags" : [ ],
    "contents" : [ {
      "title" : "同根語",
      "text" : "mo1.pk"
    } ],
    "variations" : [ ]
  }, {
    "entry" : {
      "id" : 115,
      "form" : "monatadu"
    },
    "translations" : [ {
      "title" : "漢字仮名混じり転写",
      "forms" : [ "米之集" ]
    }, {
      "title" : "体言",
      "forms" : [ "おにぎり" ]
    } ],
    "tags" : [ ],
    "contents" : [ {
      "title" : "文化",
      "text" : "炊いた飯を固めたものの塩握りが多く食される。具が入ったものはリパラオネ系が作ったものであり、タカン文化では食されない。"
    } ],
    "variations" : [ ]
  }, {
    "entry" : {
      "id" : 116,
      "form" : "namana"
    },
    "translations" : [ {
      "title" : "漢字仮名混じり転写",
      "forms" : [ "なまな" ]
    }, {
      "title" : "体言",
      "forms" : [ "死神", "死の神", "ナマナ" ]
    } ],
    "tags" : [ ],
    "contents" : [ {
      "title" : "同根語",
      "text" : "語源不明。"
    } ],
    "variations" : [ ]
  }, {
    "entry" : {
      "id" : 117,
      "form" : "namo"
    },
    "translations" : [ {
      "title" : "漢字仮名混じり転写",
      "forms" : [ "水道" ]
    }, {
      "title" : "体言",
      "forms" : [ "ナモ" ]
    } ],
    "tags" : [ "牌語借用" ],
    "contents" : [ {
      "title" : "文化",
      "text" : "ラネーメ王朝時代に制定されていた地域区分及び同地を通る幹線道路。"
    } ],
    "variations" : [ ]
  }, {
    "entry" : {
      "id" : 118,
      "form" : "uomuka"
    },
    "translations" : [ {
      "title" : "漢字仮名混じり転写",
      "forms" : [ "墨風" ]
    }, {
      "title" : "人名",
      "forms" : [ "ウオムカ" ]
    } ],
    "tags" : [ ],
    "contents" : [ {
      "title" : "文化",
      "text" : "PMCFアイル共和国タカン自治区に本拠地を置く大手自動車企業の名前でもある。"
    } ],
    "variations" : [ ]
  }, {
    "entry" : {
      "id" : 119,
      "form" : "tulijo"
    },
    "translations" : [ {
      "title" : "漢字仮名混じり転写",
      "forms" : [ "つりよ" ]
    }, {
      "title" : "体言",
      "forms" : [ "土手" ]
    } ],
    "tags" : [ ],
    "contents" : [ ],
    "variations" : [ ]
  }, {
    "entry" : {
      "id" : 120,
      "form" : "ema-lu"
    },
    "translations" : [ {
      "title" : "漢字仮名混じり転写",
      "forms" : [ "在る" ]
    }, {
      "title" : "用言",
      "forms" : [ "在る" ]
    } ],
    "tags" : [ ],
    "contents" : [ {
      "title" : "同根語",
      "text" : "hemúl.bt\nhem.bt\naima.ar\naimq.ln\naim2.pk"
    } ],
    "variations" : [ {
      "title" : "終止形",
      "form" : "emalu"
    }, {
      "title" : "連体形",
      "form" : "emala"
    }, {
      "title" : "連用形",
      "form" : "ema"
    }, {
      "title" : "命令形",
      "form" : "emaci"
    } ]
  }, {
    "entry" : {
      "id" : 121,
      "form" : "mouwa"
    },
    "translations" : [ {
      "title" : "漢字仮名混じり転写",
      "forms" : [ "別而" ]
    }, {
      "title" : "接続助詞",
      "forms" : [ "しかし" ]
    } ],
    "tags" : [ "牌語借用" ],
    "contents" : [ ],
    "variations" : [ ]
  }, {
    "entry" : {
      "id" : 122,
      "form" : "mormor-lu"
    },
    "translations" : [ {
      "title" : "漢字仮名混じり転写",
      "forms" : [ "行行る" ]
    }, {
      "title" : "用言",
      "forms" : [ "次第に増加する" ]
    }, {
      "title" : "用言",
      "forms" : [ "(連用形で)だんだん" ]
    } ],
    "tags" : [ ],
    "contents" : [ ],
    "variations" : [ {
      "title" : "終止形",
      "form" : "mormorlu"
    }, {
      "title" : "連体形",
      "form" : "mormorla"
    }, {
      "title" : "連用形",
      "form" : "mormor"
    }, {
      "title" : "命令形",
      "form" : "momorci"
    } ]
  }, {
    "entry" : {
      "id" : 123,
      "form" : "kaga"
    },
    "translations" : [ {
      "title" : "漢字仮名混じり転写",
      "forms" : [ "時" ]
    }, {
      "title" : "体言",
      "forms" : [ "時", "〜回" ]
    } ],
    "tags" : [ ],
    "contents" : [ ],
    "variations" : [ ]
  }, {
    "entry" : {
      "id" : 124,
      "form" : "aku"
    },
    "translations" : [ {
      "title" : "漢字仮名混じり転写",
      "forms" : [ "書" ]
    }, {
      "title" : "体言",
      "forms" : [ "本", "書籍" ]
    } ],
    "tags" : [ "牌語借用" ],
    "contents" : [ ],
    "variations" : [ ]
  }, {
    "entry" : {
      "id" : 125,
      "form" : "kaccen"
    },
    "translations" : [ {
      "title" : "漢字仮名混じり転写",
      "forms" : [ "互言" ]
    }, {
      "title" : "体言",
      "forms" : [ "会話" ]
    } ],
    "tags" : [ "牌語借用" ],
    "contents" : [ ],
    "variations" : [ ]
  }, {
    "entry" : {
      "id" : 126,
      "form" : "ar"
    },
    "translations" : [ {
      "title" : "漢字仮名混じり転写",
      "forms" : [ "あ", "噫" ]
    }, {
      "title" : "叫詞",
      "forms" : [ "ああ", "えっと" ]
    } ],
    "tags" : [ ],
    "contents" : [ {
      "title" : "同根語",
      "text" : "a.pk\ná.bt\nhá.bt"
    } ],
    "variations" : [ ]
  }, {
    "entry" : {
      "id" : 127,
      "form" : "ka"
    },
    "translations" : [ {
      "title" : "漢字仮名混じり転写",
      "forms" : [ "此" ]
    }, {
      "title" : "体言",
      "forms" : [ "これ" ]
    } ],
    "tags" : [ ],
    "contents" : [ ],
    "variations" : [ ]
  }, {
    "entry" : {
      "id" : 128,
      "form" : "sisitu"
    },
    "translations" : [ {
      "title" : "漢字仮名混じり転写",
      "forms" : [ "使術" ]
    }, {
      "title" : "体言",
      "forms" : [ "使い方" ]
    } ],
    "tags" : [ "牌語借用" ],
    "contents" : [ ],
    "variations" : [ ]
  }, {
    "entry" : {
      "id" : 129,
      "form" : "imik-u"
    },
    "translations" : [ {
      "title" : "漢字仮名混じり転写",
      "forms" : [ "思く" ]
    }, {
      "title" : "用言",
      "forms" : [ "思う", "考える" ]
    } ],
    "tags" : [ ],
    "contents" : [ {
      "title" : "同根語",
      "text" : "imika.ar"
    } ],
    "variations" : [ {
      "title" : "終止形",
      "form" : "imiku"
    }, {
      "title" : "連体形",
      "form" : "imika"
    }, {
      "title" : "連用形",
      "form" : "imike"
    }, {
      "title" : "命令形",
      "form" : "imiki"
    } ]
  }, {
    "entry" : {
      "id" : 130,
      "form" : "moga"
    },
    "translations" : [ {
      "title" : "漢字仮名混じり転写",
      "forms" : [ "色" ]
    }, {
      "title" : "体言",
      "forms" : [ "色", "様子" ]
    } ],
    "tags" : [ ],
    "contents" : [ {
      "title" : "同根語",
      "text" : "pok.pk\npoga.ar"
    } ],
    "variations" : [ ]
  }, {
    "entry" : {
      "id" : 131,
      "form" : "kuwi"
    },
    "translations" : [ {
      "title" : "漢字仮名混じり転写",
      "forms" : [ "傷" ]
    }, {
      "title" : "体言",
      "forms" : [ "傷" ]
    } ],
    "tags" : [ ],
    "contents" : [ {
      "title" : "同根語",
      "text" : "gui2.pk\nngui.ar"
    } ],
    "variations" : [ ]
  }, {
    "entry" : {
      "id" : 132,
      "form" : "na-lu"
    },
    "translations" : [ {
      "title" : "漢字仮名混じり転写",
      "forms" : [ "静る" ]
    }, {
      "title" : "用言",
      "forms" : [ "静かだ", "静かな" ]
    } ],
    "tags" : [ ],
    "contents" : [ {
      "title" : "同根語",
      "text" : "anaa.ar\nna1.pk"
    } ],
    "variations" : [ {
      "title" : "終止形",
      "form" : "nalu"
    }, {
      "title" : "連体形",
      "form" : "nala"
    }, {
      "title" : "連用形",
      "form" : "na"
    }, {
      "title" : "命令形",
      "form" : "naci"
    } ]
  }, {
    "entry" : {
      "id" : 133,
      "form" : "tanna"
    },
    "translations" : [ {
      "title" : "漢字仮名混じり転写",
      "forms" : [ "皇水" ]
    }, {
      "title" : "体言",
      "forms" : [ "タンナ（マナナ島とタカン島の間の海域）" ]
    } ],
    "tags" : [ ],
    "contents" : [ ],
    "variations" : [ ]
  }, {
    "entry" : {
      "id" : 134,
      "form" : "kjabetu"
    },
    "translations" : [ {
      "title" : "漢字仮名混じり転写",
      "forms" : [ "心圧" ]
    }, {
      "title" : "体言",
      "forms" : [ "心が圧されること", "ヒャーベッ" ]
    } ],
    "tags" : [ "牌語借用" ],
    "contents" : [ {
      "title" : "",
      "text" : "皇論において忌まれる。パイグから借用したのは音のみであり、語形はタカン側で成立したものと思われる。kjabetuという単語自体はタカンからパイグhia1 bet2へと借用された。"
    },{
      "title" : "同根語",
      "text" : "hia1 bet2.pk"
    } ],
    "variations" : [ ]
  }, {
    "entry" : {
      "id" : 135,
      "form" : "tomu"
    },
    "translations" : [ {
      "title" : "漢字仮名混じり転写",
      "forms" : [ "島" ]
    }, {
      "title" : "体言",
      "forms" : [ "島" ]
    } ],
    "tags" : [ ],
    "contents" : [ {
      "title" : "同根語",
      "text" : "dop'iai.ar\ndop1.pk"
    } ],
    "variations" : [ ]
  }, {
    "entry" : {
      "id" : 136,
      "form" : "inin-u"
    },
    "translations" : [ {
      "title" : "漢字仮名混じり転写",
      "forms" : [ "小ぬ" ]
    }, {
      "title" : "用言",
      "forms" : [ "小さい" ]
    } ],
    "tags" : [ ],
    "contents" : [ {
      "title" : "同根語",
      "text" : "ininu.ar\nni1.pk"
    } ],
    "variations" : [ {
      "title" : "終止形",
      "form" : "ininu"
    }, {
      "title" : "連体形",
      "form" : "inina"
    }, {
      "title" : "連用形",
      "form" : "inine"
    }, {
      "title" : "命令形",
      "form" : "inini"
    } ]
  }, {
    "entry" : {
      "id" : 137,
      "form" : "cune"
    },
    "translations" : [ {
      "title" : "漢字仮名混じり転写",
      "forms" : [ "論" ]
    }, {
      "title" : "体言",
      "forms" : [ "証拠", "論", "争点", "宗教" ]
    } ],
    "tags" : [ ],
    "contents" : [ {
      "title" : "用法",
      "text" : "takama cune （皇論）"
    }, {
      "title" : "同根語",
      "text" : "zunaii.ar zuhio.ar\nzui2.pk"
    } ],
    "variations" : [ ]
  }, {
    "entry" : {
      "id" : 138,
      "form" : "ailu"
    },
    "translations" : [ {
      "title" : "漢字仮名混じり転写",
      "forms" : [ "冠" ]
    }, {
      "title" : "体言",
      "forms" : [ "アイル共和国" ]
    } ],
    "tags" : [ ],
    "contents" : [ {
      "title" : "同根語",
      "text" : "ai'r.li\nair.ar\nai2.pk\nail.pm\nailil.pm\n"
    } ],
    "variations" : [ ]
  }, {
    "entry" : {
      "id" : 139,
      "form" : "ailucuka"
    },
    "translations" : [ {
      "title" : "漢字仮名混じり転写",
      "forms" : [ "冠人" ]
    }, {
      "title" : "体言",
      "forms" : [ "アイル人" ]
    } ],
    "tags" : [ ],
    "contents" : [ ],
    "variations" : [ ]
  }, {
    "entry" : {
      "id" : 140,
      "form" : "wepica"
    },
    "translations" : [ {
      "title" : "漢字仮名混じり転写",
      "forms" : [ "淮" ]
    }, {
      "title" : "体言",
      "forms" : [ "ヴェフィス共和国" ]
    } ],
    "tags" : [ ],
    "contents" : [ ],
    "variations" : [ ]
  }, {
    "entry" : {
      "id" : 141,
      "form" : "wepicacuka"
    },
    "translations" : [ {
      "title" : "漢字仮名混じり転写",
      "forms" : [ "淮人" ]
    }, {
      "title" : "体言",
      "forms" : [ "ヴェフィス人" ]
    } ],
    "tags" : [ ],
    "contents" : [ ],
    "variations" : [ ]
  }, {
    "entry" : {
      "id" : 142,
      "form" : "momecak-u"
    },
    "translations" : [ {
      "title" : "漢字仮名混じり転写",
      "forms" : [ "受く" ]
    }, {
      "title" : "用言",
      "forms" : [ "もらう", "得る", "受ける" ]
    } ],
    "tags" : [ ],
    "contents" : [ ],
    "variations" : [ {
      "title" : "終止形",
      "form" : "momecak-u"
    }, {
      "title" : "連体形",
      "form" : "momecak-a"
    }, {
      "title" : "連用形",
      "form" : "momecak-e"
    }, {
      "title" : "命令形",
      "form" : "momecak-i"
    } ]
  }, {
    "entry" : {
      "id" : 143,
      "form" : "momemok-u"
    },
    "translations" : [ {
      "title" : "漢字仮名混じり転写",
      "forms" : [ "与く" ]
    } ],
    "tags" : [ ],
    "contents" : [ ],
    "variations" : [ {
      "title" : "終止形",
      "form" : "momemok-u"
    }, {
      "title" : "連体形",
      "form" : "momemok-a"
    }, {
      "title" : "連用形",
      "form" : "momemok-e"
    }, {
      "title" : "命令形",
      "form" : "momemok-i"
    } ]
  }, {
    "entry" : {
      "id" : 144,
      "form" : "cetageka"
    },
    "translations" : [ {
      "title" : "漢字仮名混じり転写",
      "forms" : [ "机戦" ]
    }, {
      "title" : "体言",
      "forms" : [ "机戦", "パイグ将棋" ]
    } ],
    "tags" : [ ],
    "contents" : [ ],
    "variations" : [ ]
  }, {
    "entry" : {
      "id" : 145,
      "form" : "mekacuka"
    },
    "translations" : [ {
      "title" : "漢字仮名混じり転写",
      "forms" : [ "牌人" ]
    }, {
      "title" : "体言",
      "forms" : [ "パイグ人" ]
    } ],
    "tags" : [ ],
    "contents" : [ {
      "title" : "同根語",
      "text" : "pek2 cuk2.pk"
    } ],
    "variations" : [ ]
  }, {
    "entry" : {
      "id" : 146,
      "form" : "cokaga"
    },
    "translations" : [ {
      "title" : "漢字仮名混じり転写",
      "forms" : [ "古" ]
    }, {
      "title" : "修飾性体言",
      "forms" : [ "古い" ]
    } ],
    "tags" : [ ],
    "contents" : [ {
      "title" : "同根語",
      "text" : "sau2 kak.pk\n"
    } ],
    "variations" : [ ]
  }, {
    "entry" : {
      "id" : 147,
      "form" : "belepisi"
    },
    "translations" : [ {
      "title" : "漢字仮名混じり転写",
      "forms" : [ "べれぴし" ]
    }, {
      "title" : "体言",
      "forms" : [ "遊び", "ゲーム" ]
    } ],
    "tags" : [ ],
    "contents" : [ {
      "title" : "同根語",
      "text" : "belpic.pk\nbelfez.li"
    } ],
    "variations" : [ ]
  }, {
    "entry" : {
      "id" : 148,
      "form" : "ket-u"
    },
    "translations" : [ {
      "title" : "漢字仮名混じり転写",
      "forms" : [ "善つ" ]
    }, {
      "title" : "用言",
      "forms" : [ "良い" ]
    } ],
    "tags" : [ ],
    "contents" : [ {
      "title" : "同根語",
      "text" : "kait.pk\nkaisa.ar"
    } ],
    "variations" : [ {
      "title" : "終止形",
      "form" : "ketu"
    }, {
      "title" : "連体形",
      "form" : "keta"
    }, {
      "title" : "連用形",
      "form" : "kete"
    }, {
      "title" : "命令形",
      "form" : "keti"
    } ]
  }, {
    "entry" : {
      "id" : 149,
      "form" : "maka"
    },
    "translations" : [ {
      "title" : "漢字仮名混じり転写",
      "forms" : [ "値" ]
    }, {
      "title" : "体言",
      "forms" : [ "数", "値" ]
    } ],
    "tags" : [ ],
    "contents" : [ {
      "title" : "同根語",
      "text" : "mak2.pk\nbágha.bt"
    } ],
    "variations" : [ ]
  }, {
    "entry" : {
      "id" : 150,
      "form" : "konna"
    },
    "translations" : [ {
      "title" : "漢字仮名混じり転写",
      "forms" : [ "豆水" ]
    }, {
      "title" : "体言",
      "forms" : [ "豆から得られる液体" ]
    } ],
    "tags" : [ "牌語借用" ],
    "contents" : [ ],
    "variations" : [ ]
  }, {
    "entry" : {
      "id" : 151,
      "form" : "tanke"
    },
    "translations" : [ {
      "title" : "漢字仮名混じり転写",
      "forms" : [ "皇処" ]
    }, {
      "title" : "体言",
      "forms" : [ "机戦において駒の動きが変わる場所" ]
    } ],
    "tags" : [ "牌語借用" ],
    "contents" : [ ],
    "variations" : [ ]
  }, {
    "entry" : {
      "id" : 152,
      "form" : "kengjadatu"
    },
    "translations" : [ {
      "title" : "漢字仮名混じり転写",
      "forms" : [ "地心集" ]
    }, {
      "title" : "体言",
      "forms" : [ "文化省" ]
    } ],
    "tags" : [ "牌語借用" ],
    "contents" : [ ],
    "variations" : [ ]
  }, {
    "entry" : {
      "id" : 153,
      "form" : "mogakug-u"
    },
    "translations" : [ {
      "title" : "漢字仮名混じり転写",
      "forms" : [ "色付ぐ" ]
    }, {
      "title" : "用言",
      "forms" : [ "色を付ける" ]
    } ],
    "tags" : [ ],
    "contents" : [ ],
    "variations" : [ {
      "title" : "終止形",
      "form" : "mogakugu"
    }, {
      "title" : "連体形",
      "form" : "mogakuga"
    }, {
      "title" : "連用形",
      "form" : "mogakuge"
    }, {
      "title" : "命令形",
      "form" : "mogakugi"
    } ]
  }, {
    "entry" : {
      "id" : 154,
      "form" : "cima"
    },
    "translations" : [ {
      "title" : "漢字仮名混じり転写",
      "forms" : [ "国" ]
    }, {
      "title" : "体言",
      "forms" : [ "国" ]
    } ],
    "tags" : [ ],
    "contents" : [ {
      "title" : "同根語",
      "text" : "sip1.pk\nsíbha.bt, ṣibhai.bt\nsip'ui.ar"
    } ],
    "variations" : [ ]
  }, {
    "entry" : {
      "id" : 155,
      "form" : "linman"
    },
    "translations" : [ {
      "title" : "漢字仮名混じり転写",
      "forms" : [ "清字" ]
    }, {
      "title" : "体言",
      "forms" : [ "燐字", "燐帝字母" ]
    } ],
    "tags" : [ "牌語借用" ],
    "contents" : [ ],
    "variations" : [ ]
  }, {
    "entry" : {
      "id" : 156,
      "form" : "takan=cen"
    },
    "translations" : [ {
      "title" : "漢字仮名混じり転写",
      "forms" : [ "皇言" ]
    }, {
      "title" : "体言",
      "forms" : [ "タカン語" ]
    } ],
    "tags" : [ ],
    "contents" : [ ],
    "variations" : [ ]
  }, {
    "entry" : {
      "id" : 157,
      "form" : "(i)ja-lu"
    },
    "translations" : [ {
      "title" : "漢字仮名混じり転写",
      "forms" : [ "心る" ]
    }, {
      "title" : "補助用言",
      "forms" : [ "～したい", "～するつもりだ" ]
    } ],
    "tags" : [ ],
    "contents" : [ {
      "title" : "用法",
      "text" : "意志・欲求などを表す。"
    }, {
      "title" : "同根語",
      "text" : "hia1.pk\nhiya.ar\nriya.ln\nheyáúḷ.bt\nhíja.bt\nha.bt\nrijúḷ.bt"
    } ],
    "variations" : [ {
      "title" : "終止形",
      "form" : "ijalu"
    }, {
      "title" : "連体形",
      "form" : "ijala"
    }, {
      "title" : "連用形",
      "form" : "ija"
    }, {
      "title" : "命令形",
      "form" : "ijaci"
    } ]
  }, {
    "entry" : {
      "id" : 158,
      "form" : "nonenin-u"
    },
    "translations" : [ {
      "title" : "漢字仮名混じり転写",
      "forms" : [ "刺ぬ" ]
    }, {
      "title" : "用言",
      "forms" : [ "刺す" ]
    } ],
    "tags" : [ ],
    "contents" : [ {
      "title" : "同根語",
      "text" : "naunilorúḷ.bt"
    } ],
    "variations" : [ {
      "title" : "終止形",
      "form" : "noneninu"
    }, {
      "title" : "連体形",
      "form" : "nonenina"
    }, {
      "title" : "連用形",
      "form" : "nonenine"
    }, {
      "title" : "命令形",
      "form" : "nonenini"
    } ]
  }, {
    "entry" : {
      "id" : 159,
      "form" : "kug-u"
    },
    "translations" : [ {
      "title" : "漢字仮名混じり転写",
      "forms" : [ "付ぐ" ]
    }, {
      "title" : "用言",
      "forms" : [ "付ける" ]
    } ],
    "tags" : [ ],
    "contents" : [ {
      "title" : "同根語",
      "text" : "kun2.pk, kunge.ar"
    } ],
    "variations" : [ {
      "title" : "終止形",
      "form" : "kugu"
    }, {
      "title" : "連体形",
      "form" : "kuga"
    }, {
      "title" : "連用形",
      "form" : "kuge"
    }, {
      "title" : "命令形",
      "form" : "kugi"
    } ]
  }, {
    "entry" : {
      "id" : 160,
      "form" : "kewa-lu"
    },
    "translations" : [ {
      "title" : "用言",
      "forms" : [ "鋳込む", "型にはめる" ]
    } ],
    "tags" : [ ],
    "contents" : [ {
      "title" : "同根語",
      "text" : "gháyoúḷ.bt, ngaiweo.ar"
    } ],
    "variations" : [ {
      "title" : "終止形",
      "form" : "kewalu"
    }, {
      "title" : "連体形",
      "form" : "kewala"
    }, {
      "title" : "連用形",
      "form" : "kewata"
    }, {
      "title" : "命令形",
      "form" : "kewaci"
    } ]
  }, {
    "entry" : {
      "id" : 161,
      "form" : "kugecema-lu"
    },
    "translations" : [ {
      "title" : "漢字仮名混じり転写",
      "forms" : [ "付言る" ]
    }, {
      "title" : "用言",
      "forms" : [ "言い伝える" ]
    } ],
    "tags" : [ ],
    "contents" : [ ],
    "variations" : [ {
      "title" : "終止形",
      "form" : "kugecemalu"
    }, {
      "title" : "連体形",
      "form" : "kugecemala"
    }, {
      "title" : "連用形",
      "form" : "kugecema"
    }, {
      "title" : "命令形",
      "form" : "kugecemaci"
    } ]
  }, {
    "entry" : {
      "id" : 162,
      "form" : "cula"
    },
    "translations" : [ {
      "title" : "漢字仮名混じり転写",
      "forms" : [ "為ら" ]
    } ],
    "tags" : [ "方言" ],
    "contents" : [ {
      "title" : "用法",
      "text" : "cu の連体形 cola の北方方言。"
    } ],
    "variations" : [ ]
  }, {
    "entry" : {
      "id" : 163,
      "form" : "acula"
    },
    "translations" : [ ],
    "tags" : [ "方言" ],
    "contents" : [ {
      "title" : "用法",
      "text" : "acu の連体形 acola の北方方言。"
    } ],
    "variations" : [ ]
  }, {
    "entry" : {
      "id" : 164,
      "form" : "canenit-u"
    },
    "translations" : [ {
      "title" : "漢字仮名混じり転写",
      "forms" : [ "識ね入つ" ]
    }, {
      "title" : "用言",
      "forms" : [ "学ぶ" ]
    } ],
    "tags" : [ ],
    "contents" : [ ],
    "variations" : [ {
      "title" : "終止形",
      "form" : "canenitu"
    }, {
      "title" : "連体形",
      "form" : "canenita"
    }, {
      "title" : "連用形",
      "form" : "canenite"
    }, {
      "title" : "命令形",
      "form" : "caneniti"
    } ]
  }, {
    "entry" : {
      "id" : 165,
      "form" : "tad-u"
    },
    "translations" : [ {
      "title" : "漢字仮名混じり転写",
      "forms" : [ "集づ" ]
    }, {
      "title" : "用言",
      "forms" : [ "集まる" ]
    } ],
    "tags" : [ ],
    "contents" : [ ],
    "variations" : [ {
      "title" : "終止形",
      "form" : "tadu"
    }, {
      "title" : "連体形",
      "form" : "tada"
    }, {
      "title" : "連用形",
      "form" : "tade"
    }, {
      "title" : "命令形",
      "form" : "tadi"
    } ]
  }, {
    "entry" : {
      "id" : 166,
      "form" : "kijakaga"
    },
    "translations" : [ {
      "title" : "漢字仮名混じり転写",
      "forms" : [ "日時" ]
    }, {
      "title" : "体言",
      "forms" : [ "日中", "昼" ]
    } ],
    "tags" : [ ],
    "contents" : [ ],
    "variations" : [ ]
  }, {
    "entry" : {
      "id" : 167,
      "form" : "cutu"
    },
    "translations" : [ {
      "title" : "漢字仮名混じり転写",
      "forms" : [ "天" ]
    }, {
      "title" : "体言",
      "forms" : [ "天", "空" ]
    } ],
    "tags" : [ ],
    "contents" : [ ],
    "variations" : [ ]
  }, {
    "entry" : {
      "id" : 168,
      "form" : "asu"
    },
    "translations" : [ {
      "title" : "漢字仮名混じり転写",
      "forms" : [ "石" ]
    }, {
      "title" : "体言",
      "forms" : [ "石" ]
    } ],
    "tags" : [ ],
    "contents" : [ {
      "title" : "同根語",
      "text" : "asíjaúḷ.bt, asiu.ar, sy2.pk"
    } ],
    "variations" : [ ]
  }, {
    "entry" : {
      "id" : 169,
      "form" : "nimalane"
    },
    "translations" : [ {
      "title" : "漢字仮名混じり転写",
      "forms" : [ "哩" ]
    }, {
      "title" : "修飾性体言",
      "forms" : [ "リパライン語の", "リパラオネの" ]
    } ],
    "tags" : [ ],
    "contents" : [ ],
    "variations" : [ ]
  }, {
    "entry" : {
      "id" : 170,
      "form" : "takamacuka"
    },
    "translations" : [ {
      "title" : "漢字仮名混じり転写",
      "forms" : [ "皇人" ]
    }, {
      "title" : "体言",
      "forms" : [ "タカン人" ]
    } ],
    "tags" : [ ],
    "contents" : [ ],
    "variations" : [ ]
  }, {
    "entry" : {
      "id" : 171,
      "form" : "sornike"
    },
    "translations" : [ {
      "title" : "漢字仮名混じり転写",
      "forms" : [ "上学処" ]
    }, {
      "title" : "体言",
      "forms" : [ "大学" ]
    } ],
    "tags" : [ "牌語借用" ],
    "contents" : [ ],
    "variations" : [ ]
  }, {
    "entry" : {
      "id" : 172,
      "form" : "bepicasornike"
    },
    "translations" : [ {
      "title" : "漢字仮名混じり転写",
      "forms" : [ "淮上学処" ]
    }, {
      "title" : "体言",
      "forms" : [ "ヴェフィス国立研究院大学" ]
    } ],
    "tags" : [ ],
    "contents" : [ {
      "title" : "文化",
      "text" : "通常、ヴェフィスを表す語は wepica だが、この大学名では bepica とする。"
    } ],
    "variations" : [ ]
  }, {
    "entry" : {
      "id" : 173,
      "form" : "inucalita"
    },
    "translations" : [ {
      "title" : "漢字仮名混じり転写",
      "forms" : [ "川入" ]
    }, {
      "title" : "地名",
      "forms" : [ "イヌサリタ" ]
    } ],
    "tags" : [ ],
    "contents" : [ {
      "title" : "文化",
      "text" : "アイル共和国イヌシ郡の主要都市。"
    } ],
    "variations" : [ ]
  }, {
    "entry" : {
      "id" : 174,
      "form" : "coma"
    },
    "translations" : [ {
      "title" : "漢字仮名混じり転写",
      "forms" : [ "積" ]
    }, {
      "title" : "体言",
      "forms" : [ "堤" ]
    } ],
    "tags" : [ ],
    "contents" : [ ],
    "variations" : [ ]
  }, {
    "entry" : {
      "id" : 175,
      "form" : "mo"
    },
    "translations" : [ {
      "title" : "漢字仮名混じり転写",
      "forms" : [ "道" ]
    }, {
      "title" : "体言",
      "forms" : [ "道" ]
    } ],
    "tags" : [ ],
    "contents" : [ ],
    "variations" : [ ]
  }, {
    "entry" : {
      "id" : 176,
      "form" : "makati"
    },
    "translations" : [ {
      "title" : "漢字仮名混じり転写",
      "forms" : [ "天神" ]
    }, {
      "title" : "地名",
      "forms" : [ "マカティ" ]
    } ],
    "tags" : [ ],
    "contents" : [ {
      "title" : "文化",
      "text" : "アイル共和国の首都。"
    } ],
    "variations" : [ ]
  }, {
    "entry" : {
      "id" : 177,
      "form" : "mug-u"
    },
    "translations" : [ {
      "title" : "漢字仮名混じり転写",
      "forms" : [ "獣ぐ" ]
    }, {
      "title" : "用言",
      "forms" : [ "醜い" ]
    } ],
    "tags" : [ ],
    "contents" : [ {
      "title" : "同根語",
      "text" : "bháṇúḷ.bt"
    } ],
    "variations" : [ ]
  }, {
    "entry" : {
      "id" : 178,
      "form" : "tonir"
    },
    "translations" : [ {
      "title" : "漢字仮名混じり転写",
      "forms" : [ "とにー" ]
    }, {
      "title" : "体言",
      "forms" : [ "リパラオネ教の神・神族" ]
    } ],
    "tags" : [ ],
    "contents" : [ ],
    "variations" : [ ]
  }, {
    "entry" : {
      "id" : 179,
      "form" : "tarpu"
    },
    "translations" : [ {
      "title" : "漢字仮名混じり転写",
      "forms" : [ "たーぷ" ]
    }, {
      "title" : "人名",
      "forms" : [ "ターフ" ]
    } ],
    "tags" : [ ],
    "contents" : [ ],
    "variations" : [ ]
  }, {
    "entry" : {
      "id" : 180,
      "form" : "linecita"
    },
    "translations" : [ {
      "title" : "漢字仮名混じり転写",
      "forms" : [ "清た" ]
    }, {
      "title" : "体言",
      "forms" : [ "リナエスト・オルス共和国" ]
    }, {
      "title" : "修飾性体言",
      "forms" : [ "リナエストの" ]
    } ],
    "tags" : [ ],
    "contents" : [ ],
    "variations" : [ ]
  }, {
    "entry" : {
      "id" : 181,
      "form" : "kasika"
    },
    "translations" : [ {
      "title" : "漢字仮名混じり転写",
      "forms" : [ "筆席" ]
    }, {
      "title" : "人名",
      "forms" : [ "カジカ" ]
    } ],
    "tags" : [ ],
    "contents" : [ ],
    "variations" : [ ]
  }, {
    "entry" : {
      "id" : 182,
      "form" : "kuwa"
    },
    "translations" : [ {
      "title" : "漢字仮名混じり転写",
      "forms" : [ "筆" ]
    }, {
      "title" : "人名",
      "forms" : [ "クワ" ]
    } ],
    "tags" : [ ],
    "contents" : [ ],
    "variations" : [ ]
  }, {
    "entry" : {
      "id" : 183,
      "form" : "takama"
    },
    "translations" : [ {
      "title" : "漢字仮名混じり転写",
      "forms" : [ "たかま", "皇之" ]
    }, {
      "title" : "人名",
      "forms" : [ "タカマ" ]
    } ],
    "tags" : [ ],
    "contents" : [ ],
    "variations" : [ ]
  } ]
 }